{
  "generated_at": "2026-04-02T13:47:16",
  "config": {
    "total_steps": 150,
    "random_seed": 11,
    "num_miners": 6,
    "num_full_nodes": 12,
    "edge_probability": 0.25,
    "min_latency": 1.5,
    "max_latency": 3.5,
    "min_reliability": 0.9,
    "max_reliability": 1.0,
    "block_discovery_chance": 0.02,
    "ban_reputation_threshold": -10.0,
    "unban_reputation_threshold": -2.0,
    "enable_forum": true,
    "enable_attack_jamming": true,
    "active_modules": null,
    "max_hops_for_propagation": 5,
    "default_private_release_threshold": 2,
    "max_steps_of_jam_effect": 6,
    "snapshot_interval_blocks": 10
  },
  "headline_metrics": {
    "total_blocks": 1,
    "canonical_height": 0,
    "canonical_head_id": "B0",
    "orphan_blocks": 0,
    "orphan_ratio": 0.0,
    "fork_events": 0,
    "jam_events": 0,
    "network_efficiency": 4.514740685467306,
    "forum_post_count": 0,
    "forum_hottest_board": "none"
  },
  "top_miners": [
    {
      "miner_id": "M0",
      "discovered_blocks": 0
    },
    {
      "miner_id": "M1",
      "discovered_blocks": 0
    },
    {
      "miner_id": "M2",
      "discovered_blocks": 0
    },
    {
      "miner_id": "M3",
      "discovered_blocks": 0
    },
    {
      "miner_id": "M4",
      "discovered_blocks": 0
    },
    {
      "miner_id": "M5",
      "discovered_blocks": 0
    }
  ],
  "selfish_gamma": {
    "M0": 0.5833333333333334,
    "M1": 0.5,
    "M2": 0.5
  },
  "final_reputation": {},
  "miner_details": [
    {
      "miner_id": "M0",
      "strategy": "social_selfish",
      "hash_power": 0.12935335356880617,
      "mined_blocks": 0,
      "canonical_blocks": 0,
      "orphan_blocks": 0,
      "orphan_ratio": 0.0,
      "mined_share": 0.0,
      "canonical_share": 0.0,
      "mined_vs_hp_ratio": 0.0,
      "canonical_vs_hp_ratio": 0.0,
      "top_actions": [],
      "last_raw_action": "n/a",
      "last_effective_action": "n/a",
      "last_reason": "",
      "last_prompt": ""
    },
    {
      "miner_id": "M1",
      "strategy": "social_selfish",
      "hash_power": 0.16006124682899286,
      "mined_blocks": 0,
      "canonical_blocks": 0,
      "orphan_blocks": 0,
      "orphan_ratio": 0.0,
      "mined_share": 0.0,
      "canonical_share": 0.0,
      "mined_vs_hp_ratio": 0.0,
      "canonical_vs_hp_ratio": 0.0,
      "top_actions": [],
      "last_raw_action": "n/a",
      "last_effective_action": "n/a",
      "last_reason": "",
      "last_prompt": ""
    },
    {
      "miner_id": "M2",
      "strategy": "social_selfish",
      "hash_power": 0.2642686600659098,
      "mined_blocks": 0,
      "canonical_blocks": 0,
      "orphan_blocks": 0,
      "orphan_ratio": 0.0,
      "mined_share": 0.0,
      "canonical_share": 0.0,
      "mined_vs_hp_ratio": 0.0,
      "canonical_vs_hp_ratio": 0.0,
      "top_actions": [],
      "last_raw_action": "n/a",
      "last_effective_action": "n/a",
      "last_reason": "",
      "last_prompt": ""
    },
    {
      "miner_id": "M3",
      "strategy": "honest",
      "hash_power": 0.13314792344090332,
      "mined_blocks": 0,
      "canonical_blocks": 0,
      "orphan_blocks": 0,
      "orphan_ratio": 0.0,
      "mined_share": 0.0,
      "canonical_share": 0.0,
      "mined_vs_hp_ratio": 0.0,
      "canonical_vs_hp_ratio": 0.0,
      "top_actions": [],
      "last_raw_action": "n/a",
      "last_effective_action": "n/a",
      "last_reason": "",
      "last_prompt": ""
    },
    {
      "miner_id": "M4",
      "strategy": "honest",
      "hash_power": 0.14521207079672052,
      "mined_blocks": 0,
      "canonical_blocks": 0,
      "orphan_blocks": 0,
      "orphan_ratio": 0.0,
      "mined_share": 0.0,
      "canonical_share": 0.0,
      "mined_vs_hp_ratio": 0.0,
      "canonical_vs_hp_ratio": 0.0,
      "top_actions": [],
      "last_raw_action": "n/a",
      "last_effective_action": "n/a",
      "last_reason": "",
      "last_prompt": ""
    },
    {
      "miner_id": "M5",
      "strategy": "honest",
      "hash_power": 0.16795674529866725,
      "mined_blocks": 0,
      "canonical_blocks": 0,
      "orphan_blocks": 0,
      "orphan_ratio": 0.0,
      "mined_share": 0.0,
      "canonical_share": 0.0,
      "mined_vs_hp_ratio": 0.0,
      "canonical_vs_hp_ratio": 0.0,
      "top_actions": [],
      "last_raw_action": "n/a",
      "last_effective_action": "n/a",
      "last_reason": "",
      "last_prompt": ""
    }
  ]
}